{
    "sourceID":  10,
    "sourceName":  "브베형",
    "view":  "casts",
    "eventCount":  61,
    "totalAmount":  0,
    "totalOverheal":  0,
    "events":  [
                   {
                       "timestamp":  3397714,
                       "type":  "begincast",
                       "sourceID":  10,
                       "targetID":  -1,
                       "abilityGameID":  27136,
                       "fight":  25,
                       "sourceName":  "브베형",
                       "targetName":  "Environment",
                       "ability":  {
                                       "name":  "Holy Light",
                                       "guid":  27136,
                                       "abilityIcon":  "spell_holy_holybolt.jpg"
                                   }
                   },
                   {
                       "timestamp":  3398599,
                       "type":  "begincast",
                       "sourceID":  10,
                       "targetID":  -1,
                       "abilityGameID":  27136,
                       "fight":  25,
                       "sourceName":  "브베형",
                       "targetName":  "Environment",
                       "ability":  {
                                       "name":  "Holy Light",
                                       "guid":  27136,
                                       "abilityIcon":  "spell_holy_holybolt.jpg"
                                   }
                   },
                   {
                       "timestamp":  3401086,
                       "type":  "begincast",
                       "sourceID":  10,
                       "targetID":  -1,
                       "abilityGameID":  27136,
                       "fight":  25,
                       "sourceName":  "브베형",
                       "targetName":  "Environment",
                       "ability":  {
                                       "name":  "Holy Light",
                                       "guid":  27136,
                                       "abilityIcon":  "spell_holy_holybolt.jpg"
                                   }
                   },
                   {
                       "timestamp":  3402617,
                       "type":  "cast",
                       "sourceID":  10,
                       "targetID":  34,
                       "abilityGameID":  27136,
                       "fight":  25,
                       "resourceActor":  1,
                       "classResources":  [
                                              {
                                                  "amount":  13758,
                                                  "max":  840,
                                                  "type":  13758,
                                                  "cost":  443
                                              }
                                          ],
                       "hitPoints":  100,
                       "maxHitPoints":  100,
                       "attackPower":  688,
                       "spellPower":  738,
                       "armor":  15090,
                       "absorb":  0,
                       "x":  37728,
                       "y":  44374,
                       "facing":  -440,
                       "mapID":  334,
                       "versatility":  0,
                       "avoidance":  0,
                       "itemLevel":  126,
                       "sourceName":  "브베형",
                       "targetName":  "짱리치",
                       "ability":  {
                                       "name":  "Holy Light",
                                       "guid":  27136,
                                       "abilityIcon":  "spell_holy_holybolt.jpg"
                                   }
                   },
                   {
                       "timestamp":  3402773,
                       "type":  "begincast",
                       "sourceID":  10,
                       "targetID":  -1,
                       "abilityGameID":  27136,
                       "fight":  25,
                       "sourceName":  "브베형",
                       "targetName":  "Environment",
                       "ability":  {
                                       "name":  "Holy Light",
                                       "guid":  27136,
                                       "abilityIcon":  "spell_holy_holybolt.jpg"
                                   }
                   },
                   {
                       "timestamp":  3404322,
                       "type":  "cast",
                       "sourceID":  10,
                       "targetID":  31,
                       "abilityGameID":  27136,
                       "fight":  25,
                       "resourceActor":  1,
                       "classResources":  [
                                              {
                                                  "amount":  13758,
                                                  "max":  840,
                                                  "type":  13047,
                                                  "cost":  443
                                              }
                                          ],
                       "hitPoints":  100,
                       "maxHitPoints":  100,
                       "attackPower":  688,
                       "spellPower":  738,
                       "armor":  15090,
                       "absorb":  0,
                       "x":  37728,
                       "y":  44374,
                       "facing":  -440,
                       "mapID":  334,
                       "versatility":  0,
                       "avoidance":  0,
                       "itemLevel":  126,
                       "sourceName":  "브베형",
                       "targetName":  "Paka",
                       "ability":  {
                                       "name":  "Holy Light",
                                       "guid":  27136,
                                       "abilityIcon":  "spell_holy_holybolt.jpg"
                                   }
                   },
                   {
                       "timestamp":  3404323,
                       "type":  "begincast",
                       "sourceID":  10,
                       "targetID":  -1,
                       "abilityGameID":  27136,
                       "fight":  25,
                       "sourceName":  "브베형",
                       "targetName":  "Environment",
                       "ability":  {
                                       "name":  "Holy Light",
                                       "guid":  27136,
                                       "abilityIcon":  "spell_holy_holybolt.jpg"
                                   }
                   },
                   {
                       "timestamp":  3405865,
                       "type":  "cast",
                       "sourceID":  10,
                       "targetID":  28,
                       "abilityGameID":  27136,
                       "fight":  25,
                       "resourceActor":  1,
                       "classResources":  [
                                              {
                                                  "amount":  13758,
                                                  "max":  840,
                                                  "type":  12908,
                                                  "cost":  443
                                              }
                                          ],
                       "hitPoints":  100,
                       "maxHitPoints":  100,
                       "attackPower":  688,
                       "spellPower":  738,
                       "armor":  15090,
                       "absorb":  0,
                       "x":  37728,
                       "y":  44374,
                       "facing":  -412,
                       "mapID":  334,
                       "versatility":  0,
                       "avoidance":  0,
                       "itemLevel":  126,
                       "sourceName":  "브베형",
                       "targetName":  "고술요",
                       "ability":  {
                                       "name":  "Holy Light",
                                       "guid":  27136,
                                       "abilityIcon":  "spell_holy_holybolt.jpg"
                                   }
                   },
                   {
                       "timestamp":  3406017,
                       "type":  "begincast",
                       "sourceID":  10,
                       "targetID":  -1,
                       "abilityGameID":  27136,
                       "fight":  25,
                       "sourceName":  "브베형",
                       "targetName":  "Environment",
                       "ability":  {
                                       "name":  "Holy Light",
                                       "guid":  27136,
                                       "abilityIcon":  "spell_holy_holybolt.jpg"
                                   }
                   },
                   {
                       "timestamp":  3407297,
                       "type":  "cast",
                       "sourceID":  10,
                       "targetID":  3,
                       "abilityGameID":  27136,
                       "fight":  25,
                       "resourceActor":  1,
                       "classResources":  [
                                              {
                                                  "amount":  13758,
                                                  "max":  840,
                                                  "type":  12316,
                                                  "cost":  443
                                              }
                                          ],
                       "hitPoints":  100,
                       "maxHitPoints":  100,
                       "attackPower":  688,
                       "spellPower":  738,
                       "armor":  15090,
                       "absorb":  0,
                       "x":  37728,
                       "y":  44374,
                       "facing":  -457,
                       "mapID":  334,
                       "versatility":  0,
                       "avoidance":  0,
                       "itemLevel":  126,
                       "sourceName":  "브베형",
                       "targetName":  "보로꾜",
                       "ability":  {
                                       "name":  "Holy Light",
                                       "guid":  27136,
                                       "abilityIcon":  "spell_holy_holybolt.jpg"
                                   }
                   },
                   {
                       "timestamp":  3407654,
                       "type":  "begincast",
                       "sourceID":  10,
                       "targetID":  -1,
                       "abilityGameID":  27136,
                       "fight":  25,
                       "sourceName":  "브베형",
                       "targetName":  "Environment",
                       "ability":  {
                                       "name":  "Holy Light",
                                       "guid":  27136,
                                       "abilityIcon":  "spell_holy_holybolt.jpg"
                                   }
                   },
                   {
                       "timestamp":  3408928,
                       "type":  "cast",
                       "sourceID":  10,
                       "targetID":  25,
                       "abilityGameID":  27136,
                       "fight":  25,
                       "resourceActor":  1,
                       "classResources":  [
                                              {
                                                  "amount":  13758,
                                                  "max":  840,
                                                  "type":  12264,
                                                  "cost":  443
                                              }
                                          ],
                       "hitPoints":  100,
                       "maxHitPoints":  100,
                       "attackPower":  688,
                       "spellPower":  738,
                       "armor":  15090,
                       "absorb":  0,
                       "x":  37728,
                       "y":  44374,
                       "facing":  -473,
                       "mapID":  334,
                       "versatility":  0,
                       "avoidance":  0,
                       "itemLevel":  126,
                       "sourceName":  "브베형",
                       "targetName":  "플루토늄",
                       "ability":  {
                                       "name":  "Holy Light",
                                       "guid":  27136,
                                       "abilityIcon":  "spell_holy_holybolt.jpg"
                                   }
                   },
                   {
                       "timestamp":  3409358,
                       "type":  "begincast",
                       "sourceID":  10,
                       "targetID":  -1,
                       "abilityGameID":  27136,
                       "fight":  25,
                       "sourceName":  "브베형",
                       "targetName":  "Environment",
                       "ability":  {
                                       "name":  "Holy Light",
                                       "guid":  27136,
                                       "abilityIcon":  "spell_holy_holybolt.jpg"
                                   }
                   },
                   {
                       "timestamp":  3410631,
                       "type":  "cast",
                       "sourceID":  10,
                       "targetID":  12,
                       "abilityGameID":  27136,
                       "fight":  25,
                       "resourceActor":  1,
                       "classResources":  [
                                              {
                                                  "amount":  13758,
                                                  "max":  840,
                                                  "type":  12005,
                                                  "cost":  443
                                              }
                                          ],
                       "hitPoints":  100,
                       "maxHitPoints":  100,
                       "attackPower":  688,
                       "spellPower":  738,
                       "armor":  15090,
                       "absorb":  0,
                       "x":  37728,
                       "y":  44374,
                       "facing":  -448,
                       "mapID":  334,
                       "versatility":  0,
                       "avoidance":  0,
                       "itemLevel":  126,
                       "sourceName":  "브베형",
                       "targetName":  "자극사요",
                       "ability":  {
                                       "name":  "Holy Light",
                                       "guid":  27136,
                                       "abilityIcon":  "spell_holy_holybolt.jpg"
                                   }
                   },
                   {
                       "timestamp":  3410890,
                       "type":  "begincast",
                       "sourceID":  10,
                       "targetID":  -1,
                       "abilityGameID":  27136,
                       "fight":  25,
                       "sourceName":  "브베형",
                       "targetName":  "Environment",
                       "ability":  {
                                       "name":  "Holy Light",
                                       "guid":  27136,
                                       "abilityIcon":  "spell_holy_holybolt.jpg"
                                   }
                   },
                   {
                       "timestamp":  3412432,
                       "type":  "cast",
                       "sourceID":  10,
                       "targetID":  22,
                       "abilityGameID":  27136,
                       "fight":  25,
                       "resourceActor":  1,
                       "classResources":  [
                                              {
                                                  "amount":  13758,
                                                  "max":  840,
                                                  "type":  11344,
                                                  "cost":  443
                                              }
                                          ],
                       "hitPoints":  100,
                       "maxHitPoints":  100,
                       "attackPower":  688,
                       "spellPower":  738,
                       "armor":  15090,
                       "absorb":  0,
                       "x":  37728,
                       "y":  44374,
                       "facing":  -448,
                       "mapID":  334,
                       "versatility":  0,
                       "avoidance":  0,
                       "itemLevel":  126,
                       "sourceName":  "브베형",
                       "targetName":  "연은별",
                       "ability":  {
                                       "name":  "Holy Light",
                                       "guid":  27136,
                                       "abilityIcon":  "spell_holy_holybolt.jpg"
                                   }
                   },
                   {
                       "timestamp":  3412432,
                       "type":  "begincast",
                       "sourceID":  10,
                       "targetID":  -1,
                       "abilityGameID":  27136,
                       "fight":  25,
                       "sourceName":  "브베형",
                       "targetName":  "Environment",
                       "ability":  {
                                       "name":  "Holy Light",
                                       "guid":  27136,
                                       "abilityIcon":  "spell_holy_holybolt.jpg"
                                   }
                   },
                   {
                       "timestamp":  3413977,
                       "type":  "cast",
                       "sourceID":  10,
                       "targetID":  12,
                       "abilityGameID":  27136,
                       "fight":  25,
                       "resourceActor":  1,
                       "classResources":  [
                                              {
                                                  "amount":  13758,
                                                  "max":  840,
                                                  "type":  10722,
                                                  "cost":  443
                                              }
                                          ],
                       "hitPoints":  100,
                       "maxHitPoints":  100,
                       "attackPower":  688,
                       "spellPower":  738,
                       "armor":  15090,
                       "absorb":  0,
                       "x":  37728,
                       "y":  44374,
                       "facing":  -448,
                       "mapID":  334,
                       "versatility":  0,
                       "avoidance":  0,
                       "itemLevel":  126,
                       "sourceName":  "브베형",
                       "targetName":  "자극사요",
                       "ability":  {
                                       "name":  "Holy Light",
                                       "guid":  27136,
                                       "abilityIcon":  "spell_holy_holybolt.jpg"
                                   }
                   },
                   {
                       "timestamp":  3414715,
                       "type":  "begincast",
                       "sourceID":  10,
                       "targetID":  -1,
                       "abilityGameID":  27136,
                       "fight":  25,
                       "sourceName":  "브베형",
                       "targetName":  "Environment",
                       "ability":  {
                                       "name":  "Holy Light",
                                       "guid":  27136,
                                       "abilityIcon":  "spell_holy_holybolt.jpg"
                                   }
                   },
                   {
                       "timestamp":  3416260,
                       "type":  "cast",
                       "sourceID":  10,
                       "targetID":  17,
                       "abilityGameID":  27136,
                       "fight":  25,
                       "resourceActor":  1,
                       "classResources":  [
                                              {
                                                  "amount":  13758,
                                                  "max":  840,
                                                  "type":  10156,
                                                  "cost":  443
                                              }
                                          ],
                       "hitPoints":  100,
                       "maxHitPoints":  100,
                       "attackPower":  688,
                       "spellPower":  738,
                       "armor":  15090,
                       "absorb":  0,
                       "x":  37728,
                       "y":  44374,
                       "facing":  -423,
                       "mapID":  334,
                       "versatility":  0,
                       "avoidance":  0,
                       "itemLevel":  126,
                       "sourceName":  "브베형",
                       "targetName":  "성욕",
                       "ability":  {
                                       "name":  "Holy Light",
                                       "guid":  27136,
                                       "abilityIcon":  "spell_holy_holybolt.jpg"
                                   }
                   },
                   {
                       "timestamp":  3416486,
                       "type":  "begincast",
                       "sourceID":  10,
                       "targetID":  -1,
                       "abilityGameID":  27136,
                       "fight":  25,
                       "sourceName":  "브베형",
                       "targetName":  "Environment",
                       "ability":  {
                                       "name":  "Holy Light",
                                       "guid":  27136,
                                       "abilityIcon":  "spell_holy_holybolt.jpg"
                                   }
                   },
                   {
                       "timestamp":  3418035,
                       "type":  "cast",
                       "sourceID":  10,
                       "targetID":  3,
                       "abilityGameID":  27136,
                       "fight":  25,
                       "resourceActor":  1,
                       "classResources":  [
                                              {
                                                  "amount":  13758,
                                                  "max":  840,
                                                  "type":  10070,
                                                  "cost":  443
                                              }
                                          ],
                       "hitPoints":  100,
                       "maxHitPoints":  100,
                       "attackPower":  688,
                       "spellPower":  738,
                       "armor":  15090,
                       "absorb":  0,
                       "x":  37728,
                       "y":  44374,
                       "facing":  -448,
                       "mapID":  334,
                       "versatility":  0,
                       "avoidance":  0,
                       "itemLevel":  126,
                       "sourceName":  "브베형",
                       "targetName":  "보로꾜",
                       "ability":  {
                                       "name":  "Holy Light",
                                       "guid":  27136,
                                       "abilityIcon":  "spell_holy_holybolt.jpg"
                                   }
                   },
                   {
                       "timestamp":  3418035,
                       "type":  "begincast",
                       "sourceID":  10,
                       "targetID":  -1,
                       "abilityGameID":  27136,
                       "fight":  25,
                       "sourceName":  "브베형",
                       "targetName":  "Environment",
                       "ability":  {
                                       "name":  "Holy Light",
                                       "guid":  27136,
                                       "abilityIcon":  "spell_holy_holybolt.jpg"
                                   }
                   },
                   {
                       "timestamp":  3419595,
                       "type":  "cast",
                       "sourceID":  10,
                       "targetID":  6,
                       "abilityGameID":  27136,
                       "fight":  25,
                       "resourceActor":  1,
                       "classResources":  [
                                              {
                                                  "amount":  13758,
                                                  "max":  840,
                                                  "type":  9404,
                                                  "cost":  443
                                              }
                                          ],
                       "hitPoints":  100,
                       "maxHitPoints":  100,
                       "attackPower":  688,
                       "spellPower":  738,
                       "armor":  15090,
                       "absorb":  0,
                       "x":  37728,
                       "y":  44374,
                       "facing":  -425,
                       "mapID":  334,
                       "versatility":  0,
                       "avoidance":  0,
                       "itemLevel":  126,
                       "sourceName":  "브베형",
                       "targetName":  "불꽃해원",
                       "ability":  {
                                       "name":  "Holy Light",
                                       "guid":  27136,
                                       "abilityIcon":  "spell_holy_holybolt.jpg"
                                   }
                   },
                   {
                       "timestamp":  3419595,
                       "type":  "begincast",
                       "sourceID":  10,
                       "targetID":  -1,
                       "abilityGameID":  27136,
                       "fight":  25,
                       "sourceName":  "브베형",
                       "targetName":  "Environment",
                       "ability":  {
                                       "name":  "Holy Light",
                                       "guid":  27136,
                                       "abilityIcon":  "spell_holy_holybolt.jpg"
                                   }
                   },
                   {
                       "timestamp":  3421130,
                       "type":  "cast",
                       "sourceID":  10,
                       "targetID":  6,
                       "abilityGameID":  27136,
                       "fight":  25,
                       "resourceActor":  1,
                       "classResources":  [
                                              {
                                                  "amount":  13758,
                                                  "max":  840,
                                                  "type":  8975,
                                                  "cost":  443
                                              }
                                          ],
                       "hitPoints":  100,
                       "maxHitPoints":  100,
                       "attackPower":  688,
                       "spellPower":  738,
                       "armor":  15090,
                       "absorb":  0,
                       "x":  37728,
                       "y":  44374,
                       "facing":  -453,
                       "mapID":  334,
                       "versatility":  0,
                       "avoidance":  0,
                       "itemLevel":  126,
                       "sourceName":  "브베형",
                       "targetName":  "불꽃해원",
                       "ability":  {
                                       "name":  "Holy Light",
                                       "guid":  27136,
                                       "abilityIcon":  "spell_holy_holybolt.jpg"
                                   }
                   },
                   {
                       "timestamp":  3421499,
                       "type":  "begincast",
                       "sourceID":  10,
                       "targetID":  -1,
                       "abilityGameID":  27136,
                       "fight":  25,
                       "sourceName":  "브베형",
                       "targetName":  "Environment",
                       "ability":  {
                                       "name":  "Holy Light",
                                       "guid":  27136,
                                       "abilityIcon":  "spell_holy_holybolt.jpg"
                                   }
                   },
                   {
                       "timestamp":  3422088,
                       "type":  "begincast",
                       "sourceID":  10,
                       "targetID":  -1,
                       "abilityGameID":  27136,
                       "fight":  25,
                       "sourceName":  "브베형",
                       "targetName":  "Environment",
                       "ability":  {
                                       "name":  "Holy Light",
                                       "guid":  27136,
                                       "abilityIcon":  "spell_holy_holybolt.jpg"
                                   }
                   },
                   {
                       "timestamp":  3423615,
                       "type":  "cast",
                       "sourceID":  10,
                       "targetID":  11,
                       "abilityGameID":  27136,
                       "fight":  25,
                       "resourceActor":  1,
                       "classResources":  [
                                              {
                                                  "amount":  13758,
                                                  "max":  840,
                                                  "type":  8212,
                                                  "cost":  442
                                              }
                                          ],
                       "hitPoints":  100,
                       "maxHitPoints":  100,
                       "attackPower":  688,
                       "spellPower":  738,
                       "armor":  15090,
                       "absorb":  0,
                       "x":  37712,
                       "y":  44289,
                       "facing":  -423,
                       "mapID":  334,
                       "versatility":  0,
                       "avoidance":  0,
                       "itemLevel":  126,
                       "targetMarker":  1,
                       "sourceName":  "브베형",
                       "targetName":  "상냥한꽃순이",
                       "ability":  {
                                       "name":  "Holy Light",
                                       "guid":  27136,
                                       "abilityIcon":  "spell_holy_holybolt.jpg"
                                   }
                   },
                   {
                       "timestamp":  3423717,
                       "type":  "begincast",
                       "sourceID":  10,
                       "targetID":  -1,
                       "abilityGameID":  27136,
                       "fight":  25,
                       "sourceName":  "브베형",
                       "targetName":  "Environment",
                       "ability":  {
                                       "name":  "Holy Light",
                                       "guid":  27136,
                                       "abilityIcon":  "spell_holy_holybolt.jpg"
                                   }
                   },
                   {
                       "timestamp":  3425267,
                       "type":  "cast",
                       "sourceID":  10,
                       "targetID":  17,
                       "abilityGameID":  27136,
                       "fight":  25,
                       "resourceActor":  1,
                       "classResources":  [
                                              {
                                                  "amount":  13758,
                                                  "max":  840,
                                                  "type":  7709,
                                                  "cost":  442
                                              }
                                          ],
                       "hitPoints":  100,
                       "maxHitPoints":  100,
                       "attackPower":  688,
                       "spellPower":  738,
                       "armor":  15090,
                       "absorb":  0,
                       "x":  37712,
                       "y":  44289,
                       "facing":  -423,
                       "mapID":  334,
                       "versatility":  0,
                       "avoidance":  0,
                       "itemLevel":  126,
                       "sourceName":  "브베형",
                       "targetName":  "성욕",
                       "ability":  {
                                       "name":  "Holy Light",
                                       "guid":  27136,
                                       "abilityIcon":  "spell_holy_holybolt.jpg"
                                   }
                   },
                   {
                       "timestamp":  3425267,
                       "type":  "begincast",
                       "sourceID":  10,
                       "targetID":  -1,
                       "abilityGameID":  27136,
                       "fight":  25,
                       "sourceName":  "브베형",
                       "targetName":  "Environment",
                       "ability":  {
                                       "name":  "Holy Light",
                                       "guid":  27136,
                                       "abilityIcon":  "spell_holy_holybolt.jpg"
                                   }
                   },
                   {
                       "timestamp":  3426834,
                       "type":  "cast",
                       "sourceID":  10,
                       "targetID":  17,
                       "abilityGameID":  27136,
                       "fight":  25,
                       "resourceActor":  1,
                       "classResources":  [
                                              {
                                                  "amount":  13758,
                                                  "max":  840,
                                                  "type":  7550,
                                                  "cost":  442
                                              }
                                          ],
                       "hitPoints":  100,
                       "maxHitPoints":  100,
                       "attackPower":  688,
                       "spellPower":  738,
                       "armor":  15090,
                       "absorb":  0,
                       "x":  37712,
                       "y":  44289,
                       "facing":  -423,
                       "mapID":  334,
                       "versatility":  0,
                       "avoidance":  0,
                       "itemLevel":  126,
                       "sourceName":  "브베형",
                       "targetName":  "성욕",
                       "ability":  {
                                       "name":  "Holy Light",
                                       "guid":  27136,
                                       "abilityIcon":  "spell_holy_holybolt.jpg"
                                   }
                   },
                   {
                       "timestamp":  3426834,
                       "type":  "begincast",
                       "sourceID":  10,
                       "targetID":  -1,
                       "abilityGameID":  27136,
                       "fight":  25,
                       "sourceName":  "브베형",
                       "targetName":  "Environment",
                       "ability":  {
                                       "name":  "Holy Light",
                                       "guid":  27136,
                                       "abilityIcon":  "spell_holy_holybolt.jpg"
                                   }
                   },
                   {
                       "timestamp":  3428362,
                       "type":  "cast",
                       "sourceID":  10,
                       "targetID":  12,
                       "abilityGameID":  27136,
                       "fight":  25,
                       "resourceActor":  1,
                       "classResources":  [
                                              {
                                                  "amount":  13758,
                                                  "max":  840,
                                                  "type":  7345,
                                                  "cost":  442
                                              }
                                          ],
                       "hitPoints":  100,
                       "maxHitPoints":  100,
                       "attackPower":  688,
                       "spellPower":  738,
                       "armor":  15090,
                       "absorb":  0,
                       "x":  37712,
                       "y":  44289,
                       "facing":  -423,
                       "mapID":  334,
                       "versatility":  0,
                       "avoidance":  0,
                       "itemLevel":  126,
                       "sourceName":  "브베형",
                       "targetName":  "자극사요",
                       "ability":  {
                                       "name":  "Holy Light",
                                       "guid":  27136,
                                       "abilityIcon":  "spell_holy_holybolt.jpg"
                                   }
                   },
                   {
                       "timestamp":  3428601,
                       "type":  "begincast",
                       "sourceID":  10,
                       "targetID":  -1,
                       "abilityGameID":  27136,
                       "fight":  25,
                       "sourceName":  "브베형",
                       "targetName":  "Environment",
                       "ability":  {
                                       "name":  "Holy Light",
                                       "guid":  27136,
                                       "abilityIcon":  "spell_holy_holybolt.jpg"
                                   }
                   },
                   {
                       "timestamp":  3430160,
                       "type":  "cast",
                       "sourceID":  10,
                       "targetID":  3,
                       "abilityGameID":  27136,
                       "fight":  25,
                       "resourceActor":  1,
                       "classResources":  [
                                              {
                                                  "amount":  13758,
                                                  "max":  840,
                                                  "type":  6628,
                                                  "cost":  442
                                              }
                                          ],
                       "hitPoints":  74,
                       "maxHitPoints":  100,
                       "attackPower":  688,
                       "spellPower":  738,
                       "armor":  15090,
                       "absorb":  0,
                       "x":  37712,
                       "y":  44289,
                       "facing":  -423,
                       "mapID":  334,
                       "versatility":  0,
                       "avoidance":  0,
                       "itemLevel":  126,
                       "sourceName":  "브베형",
                       "targetName":  "보로꾜",
                       "ability":  {
                                       "name":  "Holy Light",
                                       "guid":  27136,
                                       "abilityIcon":  "spell_holy_holybolt.jpg"
                                   }
                   },
                   {
                       "timestamp":  3430161,
                       "type":  "begincast",
                       "sourceID":  10,
                       "targetID":  -1,
                       "abilityGameID":  27136,
                       "fight":  25,
                       "sourceName":  "브베형",
                       "targetName":  "Environment",
                       "ability":  {
                                       "name":  "Holy Light",
                                       "guid":  27136,
                                       "abilityIcon":  "spell_holy_holybolt.jpg"
                                   }
                   },
                   {
                       "timestamp":  3431676,
                       "type":  "cast",
                       "sourceID":  10,
                       "targetID":  12,
                       "abilityGameID":  27136,
                       "fight":  25,
                       "resourceActor":  1,
                       "classResources":  [
                                              {
                                                  "amount":  13758,
                                                  "max":  840,
                                                  "type":  6468,
                                                  "cost":  442
                                              }
                                          ],
                       "hitPoints":  74,
                       "maxHitPoints":  100,
                       "attackPower":  688,
                       "spellPower":  738,
                       "armor":  15090,
                       "absorb":  0,
                       "x":  37712,
                       "y":  44289,
                       "facing":  -423,
                       "mapID":  334,
                       "versatility":  0,
                       "avoidance":  0,
                       "itemLevel":  126,
                       "sourceName":  "브베형",
                       "targetName":  "자극사요",
                       "ability":  {
                                       "name":  "Holy Light",
                                       "guid":  27136,
                                       "abilityIcon":  "spell_holy_holybolt.jpg"
                                   }
                   },
                   {
                       "timestamp":  3431735,
                       "type":  "cast",
                       "sourceID":  10,
                       "targetID":  -1,
                       "abilityGameID":  28499,
                       "fight":  25,
                       "resourceActor":  1,
                       "classResources":  [
                                              {
                                                  "amount":  13758,
                                                  "max":  0,
                                                  "type":  5628,
                                                  "cost":  442
                                              }
                                          ],
                       "hitPoints":  74,
                       "maxHitPoints":  100,
                       "attackPower":  688,
                       "spellPower":  738,
                       "armor":  15090,
                       "absorb":  0,
                       "x":  37712,
                       "y":  44289,
                       "facing":  -423,
                       "mapID":  334,
                       "versatility":  0,
                       "avoidance":  0,
                       "itemLevel":  126,
                       "sourceName":  "브베형",
                       "targetName":  "Environment",
                       "ability":  {
                                       "name":  "Restore Mana",
                                       "guid":  28499,
                                       "abilityIcon":  "inv_potion_137.jpg"
                                   }
                   },
                   {
                       "timestamp":  3432368,
                       "type":  "cast",
                       "sourceID":  10,
                       "targetID":  -1,
                       "abilityGameID":  20216,
                       "fight":  25,
                       "resourceActor":  1,
                       "classResources":  [
                                              {
                                                  "amount":  13758,
                                                  "max":  88,
                                                  "type":  7664,
                                                  "cost":  442
                                              }
                                          ],
                       "hitPoints":  74,
                       "maxHitPoints":  100,
                       "attackPower":  688,
                       "spellPower":  738,
                       "armor":  15090,
                       "absorb":  0,
                       "x":  37712,
                       "y":  44289,
                       "facing":  -423,
                       "mapID":  334,
                       "versatility":  0,
                       "avoidance":  0,
                       "itemLevel":  126,
                       "sourceName":  "브베형",
                       "targetName":  "Environment",
                       "ability":  {
                                       "name":  "Divine Favor",
                                       "guid":  20216,
                                       "abilityIcon":  "spell_holy_heal.jpg"
                                   }
                   },
                   {
                       "timestamp":  3432718,
                       "type":  "begincast",
                       "sourceID":  10,
                       "targetID":  -1,
                       "abilityGameID":  27136,
                       "fight":  25,
                       "sourceName":  "브베형",
                       "targetName":  "Environment",
                       "ability":  {
                                       "name":  "Holy Light",
                                       "guid":  27136,
                                       "abilityIcon":  "spell_holy_holybolt.jpg"
                                   }
                   },
                   {
                       "timestamp":  3434261,
                       "type":  "cast",
                       "sourceID":  10,
                       "targetID":  35,
                       "abilityGameID":  27136,
                       "fight":  25,
                       "resourceActor":  1,
                       "classResources":  [
                                              {
                                                  "amount":  13758,
                                                  "max":  840,
                                                  "type":  7942,
                                                  "cost":  442
                                              }
                                          ],
                       "hitPoints":  81,
                       "maxHitPoints":  100,
                       "attackPower":  688,
                       "spellPower":  738,
                       "armor":  15090,
                       "absorb":  0,
                       "x":  37712,
                       "y":  44289,
                       "facing":  -423,
                       "mapID":  334,
                       "versatility":  0,
                       "avoidance":  0,
                       "itemLevel":  126,
                       "sourceName":  "브베형",
                       "targetName":  "운이없누",
                       "ability":  {
                                       "name":  "Holy Light",
                                       "guid":  27136,
                                       "abilityIcon":  "spell_holy_holybolt.jpg"
                                   }
                   },
                   {
                       "timestamp":  3434262,
                       "type":  "begincast",
                       "sourceID":  10,
                       "targetID":  -1,
                       "abilityGameID":  27136,
                       "fight":  25,
                       "sourceName":  "브베형",
                       "targetName":  "Environment",
                       "ability":  {
                                       "name":  "Holy Light",
                                       "guid":  27136,
                                       "abilityIcon":  "spell_holy_holybolt.jpg"
                                   }
                   },
                   {
                       "timestamp":  3435807,
                       "type":  "cast",
                       "sourceID":  10,
                       "targetID":  22,
                       "abilityGameID":  27136,
                       "fight":  25,
                       "resourceActor":  1,
                       "classResources":  [
                                              {
                                                  "amount":  13758,
                                                  "max":  840,
                                                  "type":  7741,
                                                  "cost":  442
                                              }
                                          ],
                       "hitPoints":  82,
                       "maxHitPoints":  100,
                       "attackPower":  688,
                       "spellPower":  738,
                       "armor":  15090,
                       "absorb":  0,
                       "x":  37712,
                       "y":  44289,
                       "facing":  -423,
                       "mapID":  334,
                       "versatility":  0,
                       "avoidance":  0,
                       "itemLevel":  126,
                       "sourceName":  "브베형",
                       "targetName":  "연은별",
                       "ability":  {
                                       "name":  "Holy Light",
                                       "guid":  27136,
                                       "abilityIcon":  "spell_holy_holybolt.jpg"
                                   }
                   },
                   {
                       "timestamp":  3435987,
                       "type":  "begincast",
                       "sourceID":  10,
                       "targetID":  -1,
                       "abilityGameID":  27136,
                       "fight":  25,
                       "sourceName":  "브베형",
                       "targetName":  "Environment",
                       "ability":  {
                                       "name":  "Holy Light",
                                       "guid":  27136,
                                       "abilityIcon":  "spell_holy_holybolt.jpg"
                                   }
                   },
                   {
                       "timestamp":  3437522,
                       "type":  "cast",
                       "sourceID":  10,
                       "targetID":  19,
                       "abilityGameID":  27136,
                       "fight":  25,
                       "resourceActor":  1,
                       "classResources":  [
                                              {
                                                  "amount":  13758,
                                                  "max":  840,
                                                  "type":  7133,
                                                  "cost":  442
                                              }
                                          ],
                       "hitPoints":  87,
                       "maxHitPoints":  100,
                       "attackPower":  688,
                       "spellPower":  738,
                       "armor":  15090,
                       "absorb":  0,
                       "x":  37712,
                       "y":  44289,
                       "facing":  -423,
                       "mapID":  334,
                       "versatility":  0,
                       "avoidance":  0,
                       "itemLevel":  126,
                       "sourceName":  "브베형",
                       "targetName":  "죤맹굳",
                       "ability":  {
                                       "name":  "Holy Light",
                                       "guid":  27136,
                                       "abilityIcon":  "spell_holy_holybolt.jpg"
                                   }
                   },
                   {
                       "timestamp":  3438007,
                       "type":  "begincast",
                       "sourceID":  10,
                       "targetID":  -1,
                       "abilityGameID":  27136,
                       "fight":  25,
                       "sourceName":  "브베형",
                       "targetName":  "Environment",
                       "ability":  {
                                       "name":  "Holy Light",
                                       "guid":  27136,
                                       "abilityIcon":  "spell_holy_holybolt.jpg"
                                   }
                   },
                   {
                       "timestamp":  3439548,
                       "type":  "cast",
                       "sourceID":  10,
                       "targetID":  79,
                       "abilityGameID":  27136,
                       "fight":  25,
                       "resourceActor":  1,
                       "classResources":  [
                                              {
                                                  "amount":  13758,
                                                  "max":  840,
                                                  "type":  6935,
                                                  "cost":  442
                                              }
                                          ],
                       "hitPoints":  93,
                       "maxHitPoints":  100,
                       "attackPower":  688,
                       "spellPower":  738,
                       "armor":  15090,
                       "absorb":  0,
                       "x":  37712,
                       "y":  44289,
                       "facing":  -423,
                       "mapID":  334,
                       "versatility":  0,
                       "avoidance":  0,
                       "itemLevel":  126,
                       "sourceName":  "브베형",
                       "targetName":  "글린시아",
                       "ability":  {
                                       "name":  "Holy Light",
                                       "guid":  27136,
                                       "abilityIcon":  "spell_holy_holybolt.jpg"
                                   }
                   },
                   {
                       "timestamp":  3439548,
                       "type":  "begincast",
                       "sourceID":  10,
                       "targetID":  -1,
                       "abilityGameID":  27136,
                       "fight":  25,
                       "sourceName":  "브베형",
                       "targetName":  "Environment",
                       "ability":  {
                                       "name":  "Holy Light",
                                       "guid":  27136,
                                       "abilityIcon":  "spell_holy_holybolt.jpg"
                                   }
                   },
                   {
                       "timestamp":  3440956,
                       "type":  "begincast",
                       "sourceID":  10,
                       "targetID":  -1,
                       "abilityGameID":  27136,
                       "fight":  25,
                       "sourceName":  "브베형",
                       "targetName":  "Environment",
                       "ability":  {
                                       "name":  "Holy Light",
                                       "guid":  27136,
                                       "abilityIcon":  "spell_holy_holybolt.jpg"
                                   }
                   },
                   {
                       "timestamp":  3442283,
                       "type":  "begincast",
                       "sourceID":  10,
                       "targetID":  -1,
                       "abilityGameID":  27136,
                       "fight":  25,
                       "sourceName":  "브베형",
                       "targetName":  "Environment",
                       "ability":  {
                                       "name":  "Holy Light",
                                       "guid":  27136,
                                       "abilityIcon":  "spell_holy_holybolt.jpg"
                                   }
                   },
                   {
                       "timestamp":  3445758,
                       "type":  "begincast",
                       "sourceID":  10,
                       "targetID":  -1,
                       "abilityGameID":  27136,
                       "fight":  25,
                       "sourceName":  "브베형",
                       "targetName":  "Environment",
                       "ability":  {
                                       "name":  "Holy Light",
                                       "guid":  27136,
                                       "abilityIcon":  "spell_holy_holybolt.jpg"
                                   }
                   },
                   {
                       "timestamp":  3447737,
                       "type":  "cast",
                       "sourceID":  10,
                       "targetID":  11,
                       "abilityGameID":  27136,
                       "fight":  25,
                       "resourceActor":  1,
                       "classResources":  [
                                              {
                                                  "amount":  13758,
                                                  "max":  840,
                                                  "type":  6953,
                                                  "cost":  442
                                              }
                                          ],
                       "hitPoints":  100,
                       "maxHitPoints":  100,
                       "attackPower":  500,
                       "spellPower":  738,
                       "armor":  15090,
                       "absorb":  0,
                       "x":  37783,
                       "y":  44275,
                       "facing":  -435,
                       "mapID":  334,
                       "versatility":  0,
                       "avoidance":  0,
                       "itemLevel":  126,
                       "targetMarker":  1,
                       "sourceName":  "브베형",
                       "targetName":  "상냥한꽃순이",
                       "ability":  {
                                       "name":  "Holy Light",
                                       "guid":  27136,
                                       "abilityIcon":  "spell_holy_holybolt.jpg"
                                   }
                   },
                   {
                       "timestamp":  3447738,
                       "type":  "begincast",
                       "sourceID":  10,
                       "targetID":  -1,
                       "abilityGameID":  27136,
                       "fight":  25,
                       "sourceName":  "브베형",
                       "targetName":  "Environment",
                       "ability":  {
                                       "name":  "Holy Light",
                                       "guid":  27136,
                                       "abilityIcon":  "spell_holy_holybolt.jpg"
                                   }
                   },
                   {
                       "timestamp":  3449748,
                       "type":  "cast",
                       "sourceID":  10,
                       "targetID":  11,
                       "abilityGameID":  27136,
                       "fight":  25,
                       "resourceActor":  1,
                       "classResources":  [
                                              {
                                                  "amount":  13758,
                                                  "max":  840,
                                                  "type":  6347,
                                                  "cost":  442
                                              }
                                          ],
                       "hitPoints":  100,
                       "maxHitPoints":  100,
                       "attackPower":  500,
                       "spellPower":  738,
                       "armor":  15090,
                       "absorb":  0,
                       "x":  37783,
                       "y":  44275,
                       "facing":  -421,
                       "mapID":  334,
                       "versatility":  0,
                       "avoidance":  0,
                       "itemLevel":  126,
                       "targetMarker":  1,
                       "sourceName":  "브베형",
                       "targetName":  "상냥한꽃순이",
                       "ability":  {
                                       "name":  "Holy Light",
                                       "guid":  27136,
                                       "abilityIcon":  "spell_holy_holybolt.jpg"
                                   }
                   },
                   {
                       "timestamp":  3449749,
                       "type":  "begincast",
                       "sourceID":  10,
                       "targetID":  -1,
                       "abilityGameID":  27136,
                       "fight":  25,
                       "sourceName":  "브베형",
                       "targetName":  "Environment",
                       "ability":  {
                                       "name":  "Holy Light",
                                       "guid":  27136,
                                       "abilityIcon":  "spell_holy_holybolt.jpg"
                                   }
                   },
                   {
                       "timestamp":  3451766,
                       "type":  "cast",
                       "sourceID":  10,
                       "targetID":  11,
                       "abilityGameID":  27136,
                       "fight":  25,
                       "resourceActor":  1,
                       "classResources":  [
                                              {
                                                  "amount":  13758,
                                                  "max":  840,
                                                  "type":  6177,
                                                  "cost":  442
                                              }
                                          ],
                       "hitPoints":  100,
                       "maxHitPoints":  100,
                       "attackPower":  500,
                       "spellPower":  738,
                       "armor":  15090,
                       "absorb":  0,
                       "x":  37783,
                       "y":  44275,
                       "facing":  -441,
                       "mapID":  334,
                       "versatility":  0,
                       "avoidance":  0,
                       "itemLevel":  126,
                       "targetMarker":  1,
                       "sourceName":  "브베형",
                       "targetName":  "상냥한꽃순이",
                       "ability":  {
                                       "name":  "Holy Light",
                                       "guid":  27136,
                                       "abilityIcon":  "spell_holy_holybolt.jpg"
                                   }
                   },
                   {
                       "timestamp":  3451767,
                       "type":  "begincast",
                       "sourceID":  10,
                       "targetID":  -1,
                       "abilityGameID":  27136,
                       "fight":  25,
                       "sourceName":  "브베형",
                       "targetName":  "Environment",
                       "ability":  {
                                       "name":  "Holy Light",
                                       "guid":  27136,
                                       "abilityIcon":  "spell_holy_holybolt.jpg"
                                   }
                   },
                   {
                       "timestamp":  3453767,
                       "type":  "cast",
                       "sourceID":  10,
                       "targetID":  11,
                       "abilityGameID":  27136,
                       "fight":  25,
                       "resourceActor":  1,
                       "classResources":  [
                                              {
                                                  "amount":  13758,
                                                  "max":  840,
                                                  "type":  6084,
                                                  "cost":  442
                                              }
                                          ],
                       "hitPoints":  100,
                       "maxHitPoints":  100,
                       "attackPower":  500,
                       "spellPower":  738,
                       "armor":  15090,
                       "absorb":  0,
                       "x":  37783,
                       "y":  44275,
                       "facing":  -423,
                       "mapID":  334,
                       "versatility":  0,
                       "avoidance":  0,
                       "itemLevel":  126,
                       "targetMarker":  1,
                       "sourceName":  "브베형",
                       "targetName":  "상냥한꽃순이",
                       "ability":  {
                                       "name":  "Holy Light",
                                       "guid":  27136,
                                       "abilityIcon":  "spell_holy_holybolt.jpg"
                                   }
                   },
                   {
                       "timestamp":  3453767,
                       "type":  "begincast",
                       "sourceID":  10,
                       "targetID":  -1,
                       "abilityGameID":  27136,
                       "fight":  25,
                       "sourceName":  "브베형",
                       "targetName":  "Environment",
                       "ability":  {
                                       "name":  "Holy Light",
                                       "guid":  27136,
                                       "abilityIcon":  "spell_holy_holybolt.jpg"
                                   }
                   }
               ]
}